README.md
setup.py
pythoption/__init__.py
pythoption/option.py
pythoption/utils.py
pythoption.egg-info/PKG-INFO
pythoption.egg-info/SOURCES.txt
pythoption.egg-info/dependency_links.txt
pythoption.egg-info/requires.txt
pythoption.egg-info/top_level.txt
venv/__init__.py