Metadata-Version: 1.0
Name: pythoption
Version: 1.0.1
Summary: A Python library for options supporting black_scholes,binomial_tree and monte_carlo
Home-page: https://github.com/www5226448/pythoption
Author: Jude
Author-email: wangyifan7836@gmail.com
License: MIT Licence
Keywords: pip,python3,option,derivative,finance
Platform: any
